textual_wrapper/wrapper/gtk/__init__.py
textual_wrapper/wrapper/gtk/base.py
textual_wrapper/wrapper/gtk/unity.py
textual_wrapper/wrapper/__init__.py
textual_wrapper/__init__.py
textual_wrapper/child.py
textual_wrapper/keycodes.py
textual_wrapper/py.typed
textual_wrapper/types.py
textual_wrapper-0.3.1.dist-info/LICENSE
textual_wrapper-0.3.1.dist-info/METADATA
textual_wrapper-0.3.1.dist-info/WHEEL
textual_wrapper-0.3.1.dist-info/entry_points.txt
textual_wrapper-0.3.1.dist-info/RECORD
