Metadata-Version: 2.2
Name: textual-wrapper
Version: 0.3.1
Summary: GUI window wrapper around a Textual app (or any other terminal program).
Author-email: Dominic Davis-Foster <dominic@davis-foster.co.uk>
License: MIT
Home-page: https://github.com/domdfcoding/textual-wrapper
Project-URL: Issue Tracker, https://github.com/domdfcoding/textual-wrapper/issues
Project-URL: Source Code, https://github.com/domdfcoding/textual-wrapper
Project-URL: Documentation, https://textual-wrapper.readthedocs.io/en/latest
Platform: Linux
Classifier: License :: OSI Approved :: MIT License
Classifier: Operating System :: POSIX :: Linux
Classifier: Programming Language :: Python
Classifier: Programming Language :: Python :: 3 :: Only
Classifier: Programming Language :: Python :: 3.10
Classifier: Programming Language :: Python :: 3.11
Classifier: Programming Language :: Python :: 3.12
Classifier: Programming Language :: Python :: Implementation :: CPython
Classifier: Typing :: Typed
Requires-Python: >=3.10
Requires-Dist: pygobject==3.50.0; extra == 'gtk'
Requires-Dist: pygobject==3.50.0; extra == 'all'
Provides-Extra: gtk
Provides-Extra: all
